docs/Makefile
docs/api.rst
docs/basis.rst
docs/conf.py
docs/contributing.rst
docs/driver.rst
docs/faq.rst
docs/favicon.ico
docs/formatting_inputs.rst
docs/gaia.rst
docs/hipparcos.rst
docs/index.rst
docs/installation.rst
docs/kepler.rst
docs/lnlike.rst
docs/make.bat
docs/manual.rst
docs/nbody.rst
docs/orbitize_logo_500.png
docs/plot.rst
docs/priors.rst
docs/read_input.rst
docs/requirements.txt
docs/results.rst
docs/sampler.rst
docs/system.rst
docs/tutorials.rst
docs/faq/Orientation_Of_Orbit.ipynb
docs/faq/Time_Of_Periastron.ipynb
docs/tutorials/Changing_bases_tutorial.ipynb
docs/tutorials/HGCA_tutorial.ipynb
docs/tutorials/Hipparcos_IAD.ipynb
docs/tutorials/MCMC_tutorial.ipynb
docs/tutorials/MCMC_vs_OFTI.ipynb
docs/tutorials/Modifying_MCMC_initial_positions.ipynb
docs/tutorials/Modifying_Priors.ipynb
docs/tutorials/Multiplanet_Tutorial.ipynb
docs/tutorials/OFTI_tutorial.ipynb
docs/tutorials/ONeil-ObsPriors.ipynb
docs/tutorials/Plotting_tutorial.ipynb
docs/tutorials/Quick-Start.ipynb
docs/tutorials/RV_MCMC_Tutorial.ipynb
docs/tutorials/Using_nonOrbitize_Posteriors_as_Priors.ipynb
docs/tutorials/abs_astrometry.ipynb
docs/tutorials/dynesty_tutorial.ipynb
docs/tutorials/eift_hd206893.png
docs/tutorials/show-me-the-orbit.ipynb
orbitize/__init__.py
orbitize/_kepler.c
orbitize/_kepler.cpython-312-darwin.so
orbitize/_kepler.pyx
orbitize/basis.py
orbitize/driver.py
orbitize/gaia.py
orbitize/gpu_context.py
orbitize/hipparcos.py
orbitize/kepler.c
orbitize/kepler.py
orbitize/lnlike.py
orbitize/nbody.py
orbitize/plot.py
orbitize/priors.py
orbitize/read_input.py
orbitize/results.py
orbitize/sampler.py
orbitize/system.py
orbitize/example_data/GJ504.csv
orbitize/example_data/GJ504_1epoch.csv
orbitize/example_data/H000025.d
orbitize/example_data/H000026.d
orbitize/example_data/H027321.d
orbitize/example_data/H027989.d
orbitize/example_data/HD4747.csv
orbitize/example_data/HGCA_vEDR3.fits
orbitize/example_data/HIP027321.d
orbitize/example_data/HR7672_joint.csv
orbitize-3.2.1.dist-info/licenses/LICENSE
orbitize-3.2.1.dist-info/METADATA
orbitize-3.2.1.dist-info/WHEEL
orbitize-3.2.1.dist-info/top_level.txt
orbitize-3.2.1.dist-info/RECORD
