Metadata-Version: 2.4
Name: orbitize
Version: 3.2.1
License-File: LICENSE
Requires-Dist: numpy
Requires-Dist: astropy>=4
Requires-Dist: scipy
Requires-Dist: emcee>=3
Requires-Dist: ptemcee_for_orbitize
Requires-Dist: matplotlib
Requires-Dist: corner
Requires-Dist: h5py
Requires-Dist: deprecation
Requires-Dist: pytest
Requires-Dist: pandas
Requires-Dist: pyerfa
Requires-Dist: astroquery
Requires-Dist: rebound
Requires-Dist: dynesty
Dynamic: license-file
